{
  "metadata": {
    "dynasty": "tang",
    "name": "唐诗",
    "period": "618-907",
    "description": "中国诗歌发展的黄金时代，名家辈出，作品丰富",
    "count": 120,
    "version": "1.1",
    "lastUpdated": "2026-06-15"
  },
  "poems": [
    {
      "id": "tang_001",
      "title": "静夜思",
      "author": "李白",
      "dynasty": "唐",
      "dynastyCode": "tang",
      "content": "床前明月光，疑是地上霜。\n举头望明月，低头思故乡。",
      "contentType": "poetry",
      "tags": [
        "五言绝句",
        "思乡",
        "启蒙",
        "小学必背"
      ],
      "source": "《李太白集》",
      "location": "扬州",
      "wordCount": 20,
      "year": 726
    },
    {
      "id": "tang_002",
      "title": "将进酒",
      "author": "李白",
      "dynasty": "唐",
      "dynastyCode": "tang",
      "content": "君不见黄河之水天上来，奔流到海不复回。\n君不见高堂明镜悲白发，朝如青丝暮成雪。\n人生得意须尽欢，莫使金樽空对月。\n天生我材必有用，千金散尽还复来。\n烹羊宰牛且为乐，会须一饮三百杯。\n\n岑夫子，丹丘生，将进酒，杯莫停。\n与君歌一曲，请君为我倾耳听。\n钟鼓馔玉不足贵，但愿长醉不复醒。\n古来圣贤皆寂寞，惟有饮者留其名。\n陈王昔时宴平乐，斗酒十千恣欢谑。\n主人何为言少钱，径须沽取对君酌。\n五花马，千金裘，\n呼儿将出换美酒，与尔同销万古愁。",
      "contentType": "poetry",
      "tags": [
        "乐府",
        "豪放",
        "名篇",
        "高中必背",
        "酒"
      ],
      "source": "《李太白集》",
      "location": "梁园/开封",
      "wordCount": 330,
      "year": 752
    },
    {
      "id": "tang_003",
      "title": "春望",
      "author": "杜甫",
      "dynasty": "唐",
      "dynastyCode": "tang",
      "content": "国破山河在，城春草木深。\n感时花溅泪，恨别鸟惊心。\n烽火连三月，家书抵万金。\n白头搔更短，浑欲不胜簪。",
      "contentType": "poetry",
      "tags": [
        "五言律诗",
        "爱国",
        "沉郁",
        "初中必背"
      ],
      "source": "《杜工部集》",
      "location": "长安",
      "wordCount": 80,
      "year": 757
    },
    {
      "id": "tang_004",
      "title": "登高",
      "author": "杜甫",
      "dynasty": "唐",
      "dynastyCode": "tang",
      "content": "风急天高猿啸哀，渚清沙白鸟飞回。\n无边落木萧萧下，不尽长江滚滚来。\n万里悲秋常作客，百年多病独登台。\n艰难苦恨繁霜鬓，潦倒新停浊酒杯。",
      "contentType": "poetry",
      "tags": [
        "七言律诗",
        "沉郁",
        "名篇",
        "高中必背",
        "秋"
      ],
      "source": "《杜工部集》",
      "location": "夔州/白帝城",
      "wordCount": 112,
      "year": 767
    },
    {
      "id": "tang_005",
      "title": "赋得古原草送别",
      "author": "白居易",
      "dynasty": "唐",
      "dynastyCode": "tang",
      "content": "离离原上草，一岁一枯荣。\n野火烧不尽，春风吹又生。\n远芳侵古道，晴翠接荒城。\n又送王孙去，萋萋满别情。",
      "contentType": "poetry",
      "tags": [
        "五言律诗",
        "送别",
        "哲理",
        "小学必背"
      ],
      "source": "《白氏长庆集》",
      "location": "长安/渭城",
      "wordCount": 80,
      "year": 787
    },
    {
      "id": "tang_006",
      "title": "登鹳雀楼",
      "author": "王之涣",
      "dynasty": "唐",
      "dynastyCode": "tang",
      "content": "白日依山尽，黄河入海流。\n欲穷千里目，更上一层楼。",
      "contentType": "poetry",
      "tags": [
        "五言绝句",
        "哲理",
        "励志",
        "小学必背"
      ],
      "source": "《全唐诗》",
      "location": "鹳雀楼/山西永济",
      "wordCount": 20,
      "year": 700
    },
    {
      "id": "tang_007",
      "title": "出塞",
      "author": "王昌龄",
      "dynasty": "唐",
      "dynastyCode": "tang",
      "content": "秦时明月汉时关，万里长征人未还。\n但使龙城飞将在，不教胡马度阴山。",
      "contentType": "poetry",
      "tags": [
        "七言绝句",
        "边塞",
        "爱国",
        "小学必背"
      ],
      "source": "《全唐诗》",
      "location": "边塞/阴山",
      "wordCount": 28,
      "year": 740
    },
    {
      "id": "tang_008",
      "title": "送元二使安西",
      "author": "王维",
      "dynasty": "唐",
      "dynastyCode": "tang",
      "content": "渭城朝雨浥轻尘，客舍青青柳色新。\n劝君更尽一杯酒，西出阳关无故人。",
      "contentType": "poetry",
      "tags": [
        "七言绝句",
        "送别",
        "名篇",
        "小学必背"
      ],
      "source": "《王右丞集》",
      "location": "渭城/咸阳",
      "wordCount": 28,
      "year": 740
    },
    {
      "id": "tang_009",
      "title": "江雪",
      "author": "柳宗元",
      "dynasty": "唐",
      "dynastyCode": "tang",
      "content": "千山鸟飞绝，万径人踪灭。\n孤舟蓑笠翁，独钓寒江雪。",
      "contentType": "poetry",
      "tags": [
        "五言绝句",
        "山水",
        "孤独",
        "小学必背",
        "冬"
      ],
      "source": "《柳河东集》",
      "location": "永州/愚溪",
      "wordCount": 20,
      "year": 805
    },
    {
      "id": "tang_010",
      "title": "春晓",
      "author": "孟浩然",
      "dynasty": "唐",
      "dynastyCode": "tang",
      "content": "春眠不觉晓，处处闻啼鸟。\n夜来风雨声，花落知多少。",
      "contentType": "poetry",
      "tags": [
        "五言绝句",
        "田园",
        "春天",
        "小学必背"
      ],
      "source": "《孟浩然集》",
      "location": "鹿门山/襄阳",
      "wordCount": 20,
      "year": 710
    },
    {
      "id": "tang_011",
      "title": "望岳",
      "author": "杜甫",
      "dynasty": "唐",
      "dynastyCode": "tang",
      "content": "岱宗夫如何？齐鲁青未了。\n造化钟神秀，阴阳割昏晓。\n荡胸生曾云，决眦入归鸟。\n会当凌绝顶，一览众山小。",
      "contentType": "poetry",
      "tags": [
        "五言古诗",
        "山水",
        "励志",
        "初中必背"
      ],
      "source": "《杜工部集》",
      "location": "泰山/兖州",
      "wordCount": 40,
      "year": 735
    },
    {
      "id": "tang_012",
      "title": "蜀道难",
      "author": "李白",
      "dynasty": "唐",
      "dynastyCode": "tang",
      "content": "噫吁嚱，危乎高哉！\n蜀道之难，难于上青天！\n蚕丛及鱼凫，开国何茫然！\n尔来四万八千岁，不与秦塞通人烟。\n西当太白有鸟道，可以横绝峨眉巅。\n地崩山摧壮士死，然后天梯石栈相钩连。\n上有六龙回日之高标，下有冲波逆折之回川。\n黄鹤之飞尚不得过，猿猱欲度愁攀援。\n青泥何盘盘，百步九折萦岩峦。\n扪参历井仰胁息，以手抚膺坐长叹。\n\n问君西游何时还？畏途巉岩不可攀。\n但见悲鸟号古木，雄飞雌从绕林间。\n又闻子规啼夜月，愁空山。\n蜀道之难，难于上青天，使人听此凋朱颜！\n连峰去天不盈尺，枯松倒倚绝壁倚。\n飞湍瀑流争喧豗，砯崖转石万壑雷。\n其险也如此，嗟尔远道之人胡为乎来哉！\n\n剑阁峥嵘而崔嵬，一夫当关，万夫莫开。\n所守或匪亲，化为狼与豺。\n朝避猛虎，夕避长蛇；\n磨牙吮血，杀人如麻。\n锦城虽云乐，不如早还家。\n蜀道之难，难于上青天，侧身西望长咨嗟！",
      "contentType": "poetry",
      "tags": [
        "乐府",
        "豪放",
        "高中必背",
        "名篇"
      ],
      "source": "《李太白集》",
      "location": "长安/蜀地",
      "wordCount": 345,
      "year": 742
    },
    {
      "id": "tang_013",
      "title": "琵琶行",
      "author": "白居易",
      "dynasty": "唐",
      "dynastyCode": "tang",
      "content": "浔阳江头夜送客，枫叶荻花秋瑟瑟。\n主人下马客在船，举酒欲饮无管弦。\n醉不成欢惨将别，别时茫茫江浸月。\n忽闻水上琵琶声，主人忘归客不发。\n寻声暗问弹者谁，琵琶声停欲语迟。\n移船相近邀相见，添酒回灯重开宴。\n千呼万唤始出来，犹抱琵琶半遮面。\n转轴拨弦三两声，未成曲调先有情。\n弦弦掩抑声声思，似诉平生不得志。\n低眉信手续续弹，说尽心中无限事。\n轻拢慢捻抹复挑，初为《霓裳》后《六幺》。\n大弦嘈嘈如急雨，小弦切切如私语。\n嘈嘈切切错杂弹，大珠小珠落玉盘。\n间关莺语花底滑，幽咽泉流冰下难。\n冰泉冷涩弦凝绝，凝绝不通声暂歇。\n别有幽愁暗恨生，此时无声胜有声。\n银瓶乍破水浆迸，铁骑突出刀枪鸣。\n曲终收拨当心画，四弦一声如裂帛。\n东船西舫悄无言，唯见江心秋月白。\n沉吟放拨插弦中，整顿衣裳起敛容。\n自言本是京城女，家在虾蟆陵下住。\n十三学得琵琶成，名属教坊第一部。\n曲罢曾教善才服，妆成每被秋娘妒。\n五陵年少争缠头，一曲红绡不知数。\n钿头银篦击节碎，血色罗裙翻酒污。\n今年欢笑复明年，秋月春风等闲度。\n弟走从军阿姨死，暮去朝来颜色故。\n门前冷落鞍马稀，老大嫁作商人妇。\n商人重利轻别离，前月浮梁买茶去。\n去来江口守空船，绕船月明江水寒。\n夜深忽梦少年事，梦啼妆泪红阑干。\n我闻琵琶已叹息，又闻此语重唧唧。\n同是天涯沦落人，相逢何必曾相识！\n我从去年辞帝京，谪居卧病浔阳城。\n浔阳地僻无音乐，终岁不闻丝竹声。\n住近湓江地低湿，黄芦苦竹绕宅生。\n其间旦暮闻何物？杜鹃啼血猿哀鸣。\n春江花朝秋月夜，往往取酒还独倾。\n岂无山歌与村笛？呕哑嘲哳难为听。\n今夜闻君琵琶语，如听仙乐耳暂明。\n莫辞更坐弹一曲，为君翻作《琵琶行》。\n感我此言良久立，却坐促弦弦转急。\n凄凄不似向前声，满座重闻皆掩泣。\n座中泣下谁最多？江州司马青衫湿。",
      "contentType": "poetry",
      "tags": [
        "七言古诗",
        "叙事",
        "高中必背",
        "贬谪"
      ],
      "source": "《白氏长庆集》",
      "location": "江州/九江",
      "wordCount": 630,
      "year": 816
    },
    {
      "id": "tang_014",
      "title": "黄鹤楼",
      "author": "崔颢",
      "dynasty": "唐",
      "dynastyCode": "tang",
      "content": "昔人已乘黄鹤去，此地空余黄鹤楼。\n黄鹤一去不复返，白云千载空悠悠。\n晴川历历汉阳树，芳草萋萋鹦鹉洲。\n日暮乡关何处是？烟波江上使人愁。",
      "contentType": "poetry",
      "tags": [
        "七言律诗",
        "怀古",
        "思乡",
        "初中必背"
      ],
      "source": "《全唐诗》",
      "location": "黄鹤楼/武汉",
      "wordCount": 56,
      "year": 730
    },
    {
      "id": "tang_015",
      "title": "山居秋暝",
      "author": "王维",
      "dynasty": "唐",
      "dynastyCode": "tang",
      "content": "空山新雨后，天气晚来秋。\n明月松间照，清泉石上流。\n竹喧归浣女，莲动下渔舟。\n随意春芳歇，王孙自可留。",
      "contentType": "poetry",
      "tags": [
        "五言律诗",
        "山水",
        "田园",
        "高中必背"
      ],
      "source": "《王右丞集》",
      "location": "辋川/蓝田",
      "wordCount": 40,
      "year": 740
    },
    {
      "id": "tang_016",
      "title": "无题·相见时难别亦难",
      "author": "李商隐",
      "dynasty": "唐",
      "dynastyCode": "tang",
      "content": "相见时难别亦难，东风无力百花残。\n春蚕到死丝方尽，蜡炬成灰泪始干。\n晓镜但愁云鬓改，夜吟应觉月光寒。\n蓬山此去无多路，青鸟殷勤为探看。",
      "contentType": "poetry",
      "tags": [
        "七言律诗",
        "爱情",
        "初中必背"
      ],
      "source": "《李义山诗集》",
      "location": "长安",
      "wordCount": 56,
      "year": 840
    },
    {
      "id": "tang_017",
      "title": "泊秦淮",
      "author": "杜牧",
      "dynasty": "唐",
      "dynastyCode": "tang",
      "content": "烟笼寒水月笼沙，夜泊秦淮近酒家。\n商女不知亡国恨，隔江犹唱后庭花。",
      "contentType": "poetry",
      "tags": [
        "七言绝句",
        "咏史",
        "忧国",
        "初中必背"
      ],
      "source": "《樊川文集》",
      "location": "秦淮河/南京",
      "wordCount": 28,
      "year": 835
    },
    {
      "id": "tang_018",
      "title": "行路难·其一",
      "author": "李白",
      "dynasty": "唐",
      "dynastyCode": "tang",
      "content": "金樽清酒斗十千，玉盘珍羞直万钱。\n停杯投箸不能食，拔剑四顾心茫然。\n欲渡黄河冰塞川，将登太行雪满山。\n闲来垂钓碧溪上，忽复乘舟梦日边。\n行路难，行路难，多歧路，今安在？\n长风破浪会有时，直挂云帆济沧海。",
      "contentType": "poetry",
      "tags": [
        "乐府",
        "豪放",
        "初中必背"
      ],
      "source": "《李太白集》",
      "location": "长安",
      "wordCount": 82,
      "year": 744
    },
    {
      "id": "tang_019",
      "title": "酬乐天扬州初逢席上见赠",
      "author": "刘禹锡",
      "dynasty": "唐",
      "dynastyCode": "tang",
      "content": "巴山楚水凄凉地，二十三年弃置身。\n怀旧空吟闻笛赋，到乡翻似烂柯人。\n沉舟侧畔千帆过，病树前头万木春。\n今日听君歌一曲，暂凭杯酒长精神。",
      "contentType": "poetry",
      "tags": [
        "七言律诗",
        "酬答",
        "哲理",
        "初中必背"
      ],
      "source": "《刘梦得文集》",
      "location": "扬州",
      "wordCount": 56,
      "year": 826
    },
    {
      "id": "tang_020",
      "title": "登幽州台歌",
      "author": "陈子昂",
      "dynasty": "唐",
      "dynastyCode": "tang",
      "content": "前不见古人，后不见来者。\n念天地之悠悠，独怆然而涕下！",
      "contentType": "poetry",
      "tags": [
        "古体诗",
        "怀古",
        "悲愤",
        "初中必背"
      ],
      "source": "《陈伯玉集》",
      "location": "幽州台/北京",
      "wordCount": 22,
      "year": 697
    },
    {
      "id": "tang_021",
      "title": "使至塞上",
      "author": "王维",
      "dynasty": "唐",
      "dynastyCode": "tang",
      "content": "单车欲问边，属国过居延。\n征蓬出汉塞，归雁入胡天。\n大漠孤烟直，长河落日圆。\n萧关逢候骑，都护在燕然。",
      "contentType": "poetry",
      "tags": [
        "五言律诗",
        "边塞",
        "名句",
        "初中必背"
      ],
      "source": "《王右丞集》",
      "location": "河西走廊/居延",
      "wordCount": 40,
      "year": 737
    },
    {
      "id": "tang_022",
      "title": "锦瑟",
      "author": "李商隐",
      "dynasty": "唐",
      "dynastyCode": "tang",
      "content": "锦瑟无端五十弦，一弦一柱思华年。\n庄生晓梦迷蝴蝶，望帝春心托杜鹃。\n沧海月明珠有泪，蓝田日暖玉生烟。\n此情可待成追忆，只是当时已惘然。",
      "contentType": "poetry",
      "tags": [
        "七言律诗",
        "无题",
        "高中必背",
        "朦胧"
      ],
      "source": "《李义山诗集》",
      "location": "长安",
      "wordCount": 56,
      "year": 858
    },
    {
      "id": "tang_023",
      "title": "钱塘湖春行",
      "author": "白居易",
      "dynasty": "唐",
      "dynastyCode": "tang",
      "content": "孤山寺北贾亭西，水面初平云脚低。\n几处早莺争暖树，谁家新燕啄春泥。\n乱花渐欲迷人眼，浅草才能没马蹄。\n最爱湖东行不足，绿杨阴里白沙堤。",
      "contentType": "poetry",
      "tags": [
        "七言律诗",
        "写景",
        "春天",
        "初中必背"
      ],
      "source": "《白氏长庆集》",
      "location": "钱塘湖/杭州",
      "wordCount": 56,
      "year": 823
    },
    {
      "id": "tang_024",
      "title": "送杜少府之任蜀州",
      "author": "王勃",
      "dynasty": "唐",
      "dynastyCode": "tang",
      "content": "城阙辅三秦，风烟望五津。\n与君离别意，同是宦游人。\n海内存知己，天涯若比邻。\n无为在歧路，儿女共沾巾。",
      "contentType": "poetry",
      "tags": [
        "五言律诗",
        "送别",
        "初唐",
        "初中必背"
      ],
      "source": "《王子安集》",
      "location": "长安",
      "wordCount": 40,
      "year": 668
    },
    {
      "id": "tang_025",
      "title": "茅屋为秋风所破歌",
      "author": "杜甫",
      "dynasty": "唐",
      "dynastyCode": "tang",
      "content": "八月秋高风怒号，卷我屋上三重茅。\n茅飞渡江洒江郊，高者挂罥长林梢，下者飘转沉塘坳。\n南村群童欺我老无力，忍能对面为盗贼。\n公然抱茅入竹去，唇焦口燥呼不得，归来倚杖自叹息。\n俄顷风定云墨色，秋天漠漠向昏黑。\n布衾多年冷似铁，娇儿恶卧踏里裂。\n床头屋漏无干处，雨脚如麻未断绝。\n自经丧乱少睡眠，长夜沾湿何由彻！\n安得广厦千万间，大庇天下寒士俱欢颜！风雨不动安如山。\n呜呼！何时眼前突兀见此屋，吾庐独破受冻死亦足！",
      "contentType": "poetry",
      "tags": [
        "歌行体",
        "忧国忧民",
        "初中必背"
      ],
      "source": "《杜工部集》",
      "location": "成都/草堂",
      "wordCount": 170,
      "year": 761
    },
    {
      "id": "tang_026",
      "title": "师说",
      "author": "韩愈",
      "dynasty": "唐",
      "dynastyCode": "tang",
      "content": "古之学者必有师。师者，所以传道受业解惑也。人非生而知之者，孰能无惑？惑而不从师，其为惑也，终不解矣。\n生乎吾前，其闻道也固先乎吾，吾从而师之；生乎吾后，其闻道也亦先乎吾，吾从而师之。吾师道也，夫庸知其年之先后生于吾乎？是故无贵无贱，无长无少，道之所存，师之所存也。\n嗟乎！师道之不传也久矣！欲人之无惑也难矣！古之圣人，其出人也远矣，犹且从师而问焉；今之众人，其下圣人也亦远矣，而耻学于师。是故圣益圣，愚益愚。圣人之所以为圣，愚人之所以为愚，其皆出于此乎？爱其子，择师而教之；于其身也，则耻师焉，惑矣。彼童子之师，授之书而习其句读者，非吾所谓传其道解其惑者也。句读之不知，惑之不解，或师焉，或不焉，小学而大遗，吾未见其明也。巫医乐师百工之人，不耻相师。士大夫之族，曰师曰弟子云者，则群聚而笑之。问之，则曰：“彼与彼年相若也，道相似也。位卑则足羞，官盛则近谀。”呜呼！师道之不复可知矣。巫医乐师百工之人，君子不齿，今其智乃反不能及，其可怪也欤！\n圣人无常师。孔子师郯子、苌弘、师襄、老聃。郯子之徒，其贤不及孔子。孔子曰：“三人行，则必有我师。”是故弟子不必不如师，师不必贤于弟子，闻道有先后，术业有专攻，如是而已。\n李氏子蟠，年十七，好古文，六艺经传皆通习之，不拘于时，学于余。余嘉其能行古道，作《师说》以贻之。",
      "contentType": "prose",
      "tags": [
        "古文",
        "议论",
        "高中必背",
        "韩愈"
      ],
      "source": "《昌黎先生集》",
      "location": "长安",
      "wordCount": 456,
      "year": 802
    },
    {
      "id": "tang_027",
      "title": "阿房宫赋",
      "author": "杜牧",
      "dynasty": "唐",
      "dynastyCode": "tang",
      "content": "六王毕，四海一，蜀山兀，阿房出。覆压三百余里，隔离天日。骊山北构而西折，直走咸阳。二川溶溶，流入宫墙。五步一楼，十步一阁；廊腰缦回，檐牙高啄；各抱地势，钩心斗角。盘盘焉，囷囷焉，蜂房水涡，矗不知其几千万落。长桥卧波，未云何龙？复道行空，不霁何虹？高低冥迷，不知西东。歌台暖响，春光融融；舞殿冷袖，风雨凄凄。一日之内，一宫之间，而气候不齐。\n妃嫔媵嫱，王子皇孙，辞楼下殿，辇来于秦。朝歌夜弦，为秦宫人。明星荧荧，开妆镜也；绿云扰扰，梳晓鬟也；渭流涨腻，弃脂水也；烟斜雾横，焚椒兰也。雷霆乍惊，宫车过也；辘辘远听，杳不知其所之也。一肌一容，尽态极妍，缦立远视，而望幸焉。有不见者，三十六年。燕赵之收藏，韩魏之经营，齐楚之精英，几世几年，剽掠其人，倚叠如山。一旦不能有，输来其间。鼎铛玉石，金块珠砾，弃掷逦迤，秦人视之，亦不甚惜。\n嗟乎！一人之心，千万人之心也。秦爱纷奢，人亦念其家。奈何取之尽锱铢，用之如泥沙？使负栋之柱，多于南亩之农夫；架梁之椽，多于机上之工女；钉头磷磷，多于在庾之粟粒；瓦缝参差，多于周身之帛缕；直栏横槛，多于九土之城郭；管弦呕哑，多于市人之言语。使天下之人，不敢言而敢怒。独夫之心，日益骄固。戍卒叫，函谷举，楚人一炬，可怜焦土！\n呜呼！灭六国者六国也，非秦也；族秦者秦也，非天下也。嗟乎！使六国各爱其人，则足以拒秦；使秦复爱六国之人，则递三世可至万世而为君，谁得而族灭也？秦人不暇自哀，而后人哀之；后人哀之而不鉴之，亦使后人而复哀后人也。",
      "contentType": "fu",
      "tags": [
        "赋",
        "咏史",
        "高中必背",
        "杜牧"
      ],
      "source": "《樊川文集》",
      "location": "长安",
      "wordCount": 513,
      "year": 825
    },
    {
      "id": "tang_028",
      "title": "陋室铭",
      "author": "刘禹锡",
      "dynasty": "唐",
      "dynastyCode": "tang",
      "content": "山不在高，有仙则名。水不在深，有龙则灵。斯是陋室，惟吾德馨。苔痕上阶绿，草色入帘青。谈笑有鸿儒，往来无白丁。可以调素琴，阅金经。无丝竹之乱耳，无案牍之劳形。南阳诸葛庐，西蜀子云亭。孔子云：何陋之有？",
      "contentType": "prose",
      "tags": [
        "铭文",
        "托物言志",
        "初中必背",
        "刘禹锡"
      ],
      "source": "《刘梦得文集》",
      "location": "和州/安徽",
      "wordCount": 81,
      "year": 824
    },
    {
      "id": "tang_029",
      "title": "小石潭记",
      "author": "柳宗元",
      "dynasty": "唐",
      "dynastyCode": "tang",
      "content": "从小丘西行百二十步，隔篁竹，闻水声，如鸣珮环，心乐之。伐竹取道，下见小潭，水尤清冽。全石以为底，近岸，卷石底以出，为坻，为屿，为嵁，为岩。青树翠蔓，蒙络摇缀，参差披拂。\n潭中鱼可百许头，皆若空游无所依。日光下澈，影布石上，佁然不动；俶尔远逝，往来翕忽。似与游者相乐。\n潭西南而望，斗折蛇行，明灭可见。其岸势犬牙差互，不可知其源。\n坐潭上，四面竹树环合，寂寥无人，凄神寒骨，悄怆幽邃。以其境过清，不可久居，乃记之而去。\n同游者：吴武陵，龚古，余弟宗玄。隶而从者，崔氏二小生：曰恕己，曰奉壹。",
      "contentType": "prose",
      "tags": [
        "游记",
        "山水",
        "初中必背",
        "柳宗元"
      ],
      "source": "《柳河东集》",
      "location": "永州/湖南",
      "wordCount": 193,
      "year": 805
    },
    {
      "id": "tang_030",
      "title": "马说",
      "author": "韩愈",
      "dynasty": "唐",
      "dynastyCode": "tang",
      "content": "世有伯乐，然后有千里马。千里马常有，而伯乐不常有。故虽有名马，祗辱于奴隶人之手，骈死于槽枥之间，不以千里称也。\n马之千里者，一食或尽粟一石。食马者不知其能千里而食也。是马也，虽有千里之能，食不饱，力不足，才美不外见，且欲与常马等不可得，安求其能千里也？\n策之不以其道，食之不能尽其材，鸣之而不能通其意，执策而临之，曰：“天下无马！”呜呼！其真无马邪？其真不知马也！",
      "contentType": "prose",
      "tags": [
        "寓言",
        "议论",
        "初中必背",
        "韩愈"
      ],
      "source": "《昌黎先生集》",
      "location": "长安",
      "wordCount": 153,
      "year": 795
    },
    {
      "id": "tang_031",
      "title": "白雪歌送武判官归京",
      "author": "岑参",
      "dynasty": "唐",
      "dynastyCode": "tang",
      "content": "北风卷地白草折，胡天八月即飞雪。\n忽如一夜春风来，千树万树梨花开。\n散入珠帘湿罗幕，狐裘不暖锦衾薄。\n将军角弓不得控，都护铁衣冷难着。\n瀚海阑干百丈冰，愁云惨淡万里凝。\n中军置酒饮归客，胡琴琵琶与羌笛。\n纷纷暮雪下辕门，风掣红旗冻不翻。\n轮台东门送君去，去时雪满天山路。\n山回路转不见君，雪上空留马行处。",
      "contentType": "poetry",
      "tags": [
        "歌行体",
        "边塞",
        "送别",
        "初中必背"
      ],
      "source": "《岑嘉州集》",
      "location": "轮台/新疆",
      "wordCount": 126,
      "year": 754
    },
    {
      "id": "tang_032",
      "title": "早发白帝城",
      "author": "李白",
      "dynasty": "唐",
      "dynastyCode": "tang",
      "content": "朝辞白帝彩云间，千里江陵一日还。\n两岸猿声啼不住，轻舟已过万重山。",
      "contentType": "poetry",
      "tags": [
        "七言绝句",
        "写景",
        "快意",
        "小学必背"
      ],
      "source": "《李太白集》",
      "location": "白帝城/重庆",
      "wordCount": 28,
      "year": 759
    },
    {
      "id": "tang_033",
      "title": "望天门山",
      "author": "李白",
      "dynasty": "唐",
      "dynastyCode": "tang",
      "content": "天门中断楚江开，碧水东流至此回。\n两岸青山相对出，孤帆一片日边来。",
      "contentType": "poetry",
      "tags": [
        "七言绝句",
        "山水",
        "小学必背"
      ],
      "source": "《李太白集》",
      "location": "天门山/安徽",
      "wordCount": 28,
      "year": 725
    },
    {
      "id": "tang_034",
      "title": "闻王昌龄左迁龙标遥有此寄",
      "author": "李白",
      "dynasty": "唐",
      "dynastyCode": "tang",
      "content": "杨花落尽子规啼，闻道龙标过五溪。\n我寄愁心与明月，随君直到夜郎西。",
      "contentType": "poetry",
      "tags": [
        "七言绝句",
        "送别",
        "同情",
        "初中必背"
      ],
      "source": "《李太白集》",
      "location": "扬州",
      "wordCount": 28,
      "year": 753
    },
    {
      "id": "tang_035",
      "title": "游子吟",
      "author": "孟郊",
      "dynasty": "唐",
      "dynastyCode": "tang",
      "content": "慈母手中线，游子身上衣。\n临行密密缝，意恐迟迟归。\n谁言寸草心，报得三春晖。",
      "contentType": "poetry",
      "tags": [
        "五言古诗",
        "母爱",
        "名篇",
        "小学必背"
      ],
      "source": "《孟东野集》",
      "location": "溧阳/江苏",
      "wordCount": 30,
      "year": 796
    },
    {
      "id": "tang_036",
      "title": "卖炭翁",
      "author": "白居易",
      "dynasty": "唐",
      "dynastyCode": "tang",
      "content": "卖炭翁，伐薪烧炭南山中。\n满面尘灰烟火色，两鬓苍苍十指黑。\n卖炭得钱何所营？身上衣裳口中食。\n可怜身上衣正单，心忧炭贱愿天寒。\n夜来城外一尺雪，晓驾炭车辗冰辙。\n牛困人饥日已高，市南门外泥中歇。\n翩翩两骑来是谁？黄衣使者白衫儿。\n手把文书口称敕，回车叱牛牵向北。\n一车炭，千余斤，宫使驱将惜不得。\n半匹红纱一丈绫，系向牛头充炭直。",
      "contentType": "poetry",
      "tags": [
        "乐府",
        "叙事",
        "讽喻",
        "初中必背"
      ],
      "source": "《白氏长庆集》",
      "location": "长安",
      "wordCount": 135,
      "year": 806
    },
    {
      "id": "tang_037",
      "title": "赤壁",
      "author": "杜牧",
      "dynasty": "唐",
      "dynastyCode": "tang",
      "content": "折戟沉沙铁未销，自将磨洗认前朝。\n东风不与周郎便，铜雀春深锁二乔。",
      "contentType": "poetry",
      "tags": [
        "七言绝句",
        "咏史",
        "初中必背"
      ],
      "source": "《樊川文集》",
      "location": "黄州/赤壁",
      "wordCount": 28,
      "year": 842
    },
    {
      "id": "tang_038",
      "title": "江南春",
      "author": "杜牧",
      "dynasty": "唐",
      "dynastyCode": "tang",
      "content": "千里莺啼绿映红，水村山郭酒旗风。\n南朝四百八十寺，多少楼台烟雨中。",
      "contentType": "poetry",
      "tags": [
        "七言绝句",
        "写景",
        "怀古",
        "小学必背"
      ],
      "source": "《樊川文集》",
      "location": "江南",
      "wordCount": 28,
      "year": 835
    },
    {
      "id": "tang_039",
      "title": "夜雨寄北",
      "author": "李商隐",
      "dynasty": "唐",
      "dynastyCode": "tang",
      "content": "君问归期未有期，巴山夜雨涨秋池。\n何当共剪西窗烛，却话巴山夜雨时。",
      "contentType": "poetry",
      "tags": [
        "七言绝句",
        "思念",
        "初中必背"
      ],
      "source": "《李义山诗集》",
      "location": "巴蜀/四川",
      "wordCount": 28,
      "year": 850
    },
    {
      "id": "tang_040",
      "title": "雁门太守行",
      "author": "李贺",
      "dynasty": "唐",
      "dynastyCode": "tang",
      "content": "黑云压城城欲摧，甲光向日金鳞开。\n角声满天秋色里，塞上燕脂凝夜紫。\n半卷红旗临易水，霜重鼓寒声不起。\n报君黄金台上意，提携玉龙为君死。",
      "contentType": "poetry",
      "tags": [
        "乐府",
        "边塞",
        "壮烈",
        "初中必背"
      ],
      "source": "《李长吉歌诗》",
      "location": "雁门关/山西",
      "wordCount": 56,
      "year": 807
    },
    {
      "id": "tang_041",
      "title": "梦游天姥吟留别",
      "author": "李白",
      "dynasty": "唐",
      "dynastyCode": "tang",
      "content": "海客谈瀛洲，烟涛微茫信难求；\n越人语天姥，云霞明灭或可睹。\n天姥连天向天横，势拔五岳掩赤城。\n天台四万八千丈，对此欲倒东南倾。\n我欲因之梦吴越，一夜飞度镜湖月。\n湖月照我影，送我至剡溪。\n谢公宿处今尚在，渌水荡漾清猿啼。\n脚著谢公屐，身登青云梯。\n半壁见海日，空中闻天鸡。\n千岩万转路不定，迷花倚石忽已暝。\n熊咆龙吟殷岩泉，栗深林兮惊层巅。\n云青青兮欲雨，水澹澹兮生烟。\n列缺霹雳，丘峦崩摧。\n洞天石扉，訇然中开。\n青冥浩荡不见底，日月照耀金银台。\n霓为衣兮风为马，云之君兮纷纷而来下。\n虎鼓瑟兮鸾回车，仙之人兮列如麻。\n忽魂悸以魄动，恍惊起而长嗟。\n惟觉时之枕席，失向来之烟霞。\n世间行乐亦如此，古来万事东流水。\n别君去兮何时还？且放白鹿青崖间，须行即骑访名山。\n安能摧眉折腰事权贵，使我不得开心颜！",
      "contentType": "poetry",
      "tags": [
        "乐府",
        "游仙",
        "高中必背",
        "名篇"
      ],
      "source": "《李太白集》",
      "location": "越中/浙江",
      "wordCount": 284,
      "year": 746
    },
    {
      "id": "tang_042",
      "title": "枫桥夜泊",
      "author": "张继",
      "dynasty": "唐",
      "dynastyCode": "tang",
      "content": "月落乌啼霜满天，江枫渔火对愁眠。\n姑苏城外寒山寺，夜半钟声到客船。",
      "contentType": "poetry",
      "tags": [
        "七言绝句",
        "羁旅",
        "名篇",
        "小学必背"
      ],
      "source": "《全唐诗》",
      "location": "苏州/寒山寺",
      "wordCount": 28,
      "year": 756
    },
    {
      "id": "tang_043",
      "title": "回乡偶书",
      "author": "贺知章",
      "dynasty": "唐",
      "dynastyCode": "tang",
      "content": "少小离家老大回，乡音无改鬓毛衰。\n儿童相见不相识，笑问客从何处来。",
      "contentType": "poetry",
      "tags": [
        "七言绝句",
        "思乡",
        "小学必背"
      ],
      "source": "《全唐诗》",
      "location": "越州/浙江绍兴",
      "wordCount": 28,
      "year": 744
    },
    {
      "id": "tang_044",
      "title": "咏柳",
      "author": "贺知章",
      "dynasty": "唐",
      "dynastyCode": "tang",
      "content": "碧玉妆成一树高，万条垂下绿丝绦。\n不知细叶谁裁出，二月春风似剪刀。",
      "contentType": "poetry",
      "tags": [
        "七言绝句",
        "咏物",
        "春天",
        "小学必背"
      ],
      "source": "《全唐诗》",
      "location": "长安",
      "wordCount": 28,
      "year": 735
    },
    {
      "id": "tang_045",
      "title": "凉州词",
      "author": "王翰",
      "dynasty": "唐",
      "dynastyCode": "tang",
      "content": "葡萄美酒夜光杯，欲饮琵琶马上催。\n醉卧沙场君莫笑，古来征战几人回？",
      "contentType": "poetry",
      "tags": [
        "七言绝句",
        "边塞",
        "豪迈",
        "小学必背"
      ],
      "source": "《全唐诗》",
      "location": "凉州/甘肃",
      "wordCount": 28,
      "year": 710
    },
    {
      "id": "tang_046",
      "title": "滁州西涧",
      "author": "韦应物",
      "dynasty": "唐",
      "dynastyCode": "tang",
      "content": "独怜幽草涧边生，上有黄鹂深树鸣。\n春潮带雨晚来急，野渡无人舟自横。",
      "contentType": "poetry",
      "tags": [
        "七言绝句",
        "山水",
        "恬淡",
        "初中必背"
      ],
      "source": "《韦苏州集》",
      "location": "滁州/安徽",
      "wordCount": 28,
      "year": 783
    },
    {
      "id": "tang_047",
      "title": "石壕吏",
      "author": "杜甫",
      "dynasty": "唐",
      "dynastyCode": "tang",
      "content": "暮投石壕村，有吏夜捉人。老翁逾墙走，老妇出门看。\n吏呼一何怒！妇啼一何苦！\n听妇前致词：三男邺城戍。一男附书至，二男新战死。\n存者且偷生，死者长已矣！室中更无人，惟有乳下孙。\n有孙母未去，出入无完裙。老妪力虽衰，请从吏夜归，\n急应河阳役，犹得备晨炊。\n夜久语声绝，如闻泣幽咽。天明登前途，独与老翁别。",
      "contentType": "poetry",
      "tags": [
        "五言古诗",
        "叙事",
        "战乱",
        "初中必背"
      ],
      "source": "《杜工部集》",
      "location": "石壕村/河南",
      "wordCount": 120,
      "year": 759
    },
    {
      "id": "tang_048",
      "title": "望庐山瀑布",
      "author": "李白",
      "dynasty": "唐",
      "dynastyCode": "tang",
      "content": "日照香炉生紫烟，遥看瀑布挂前川。\n飞流直下三千尺，疑是银河落九天。",
      "contentType": "poetry",
      "tags": [
        "七言绝句",
        "山水",
        "夸张",
        "小学必背"
      ],
      "source": "《李太白集》",
      "location": "庐山/江西",
      "year": 726,
      "wordCount": 28
    },
    {
      "id": "tang_049",
      "title": "春江花月夜",
      "author": "张若虚",
      "dynasty": "唐",
      "dynastyCode": "tang",
      "content": "春江潮水连海平，海上明月共潮生。\n滟滟随波千万里，何处春江无月明！\n江流宛转绕芳甸，月照花林皆似霰；\n空里流霜不觉飞，汀上白沙看不见。\n江天一色无纤尘，皎皎空中孤月轮。\n江畔何人初见月？江月何年初照人？\n人生代代无穷已，江月年年望相似。\n不知江月待何人，但见长江送流水。\n白云一片去悠悠，青枫浦上不胜愁。\n谁家今夜扁舟子？何处相思明月楼？\n可怜楼上月徘徊，应照离人妆镜台。\n玉户帘中卷不去，捣衣砧上拂还来。\n此时相望不相闻，愿逐月华流照君。\n鸿雁长飞光不度，鱼龙潜跃水成文。\n昨夜闲潭梦落花，可怜春半不还家。\n江水流春去欲尽，江潭落月复西斜。\n斜月沉沉藏海雾，碣石潇湘无限路。\n不知乘月几人归，落月摇情满江树。",
      "contentType": "poetry",
      "tags": [
        "乐府",
        "孤篇压全唐",
        "哲理",
        "高中必背"
      ],
      "source": "《全唐诗》",
      "location": "扬州/江都",
      "wordCount": 252,
      "year": 650
    },
    {
      "id": "tang_050",
      "title": "别董大",
      "author": "高适",
      "dynasty": "唐",
      "dynastyCode": "tang",
      "content": "千里黄云白日曛，北风吹雁雪纷纷。\n莫愁前路无知己，天下谁人不识君。",
      "contentType": "poetry",
      "tags": [
        "七言绝句",
        "送别",
        "豪迈",
        "小学必背"
      ],
      "source": "《高常侍集》",
      "location": "睢阳/河南商丘",
      "wordCount": 28,
      "year": 747
    },
    {
      "id": "tang_051",
      "title": "赠汪伦",
      "author": "李白",
      "dynasty": "唐",
      "dynastyCode": "tang",
      "content": "李白乘舟将欲行，忽闻岸上踏歌声。\n桃花潭水深千尺，不及汪伦送我情。",
      "contentType": "poetry",
      "tags": [
        "七言绝句",
        "送别",
        "友情",
        "小学必背"
      ],
      "source": "《李太白集》",
      "location": "泾县/桃花潭",
      "wordCount": 28,
      "year": 755
    },
    {
      "id": "tang_052",
      "title": "黄鹤楼送孟浩然之广陵",
      "author": "李白",
      "dynasty": "唐",
      "dynastyCode": "tang",
      "content": "故人西辞黄鹤楼，烟花三月下扬州。\n孤帆远影碧空尽，唯见长江天际流。",
      "contentType": "poetry",
      "tags": [
        "七言绝句",
        "送别",
        "名篇",
        "小学必背"
      ],
      "source": "《李太白集》",
      "location": "黄鹤楼/武汉",
      "wordCount": 28,
      "year": 730
    },
    {
      "id": "tang_053",
      "title": "独坐敬亭山",
      "author": "李白",
      "dynasty": "唐",
      "dynastyCode": "tang",
      "content": "众鸟高飞尽，孤云独去闲。\n相看两不厌，只有敬亭山。",
      "contentType": "poetry",
      "tags": [
        "五言绝句",
        "山水",
        "孤独",
        "小学必背"
      ],
      "source": "《李太白集》",
      "location": "敬亭山/安徽宣城",
      "wordCount": 20,
      "year": 753
    },
    {
      "id": "tang_054",
      "title": "渡荆门送别",
      "author": "李白",
      "dynasty": "唐",
      "dynastyCode": "tang",
      "content": "渡远荆门外，来从楚国游。\n山随平野尽，江入大荒流。\n月下飞天镜，云生结海楼。\n仍怜故乡水，万里送行舟。",
      "contentType": "poetry",
      "tags": [
        "五言律诗",
        "送别",
        "山水",
        "初中必背"
      ],
      "source": "《李太白集》",
      "location": "荆门/湖北宜都",
      "wordCount": 40,
      "year": 724
    },
    {
      "id": "tang_055",
      "title": "月下独酌",
      "author": "李白",
      "dynasty": "唐",
      "dynastyCode": "tang",
      "content": "花间一壶酒，独酌无相亲。\n举杯邀明月，对影成三人。\n月既不解饮，影徒随我身。\n暂伴月将影，行乐须及春。\n我歌月徘徊，我舞影零乱。\n醒时同交欢，醉后各分散。\n永结无情游，相期邈云汉。",
      "contentType": "poetry",
      "tags": [
        "五言古诗",
        "孤独",
        "豪放",
        "高中必背"
      ],
      "source": "《李太白集》",
      "location": "长安",
      "wordCount": 96,
      "year": 744
    },
    {
      "id": "tang_056",
      "title": "春夜洛城闻笛",
      "author": "李白",
      "dynasty": "唐",
      "dynastyCode": "tang",
      "content": "谁家玉笛暗飞声，散入春风满洛城。\n此夜曲中闻折柳，何人不起故园情。",
      "contentType": "poetry",
      "tags": [
        "七言绝句",
        "思乡",
        "初中必背"
      ],
      "source": "《李太白集》",
      "location": "洛阳/河南",
      "wordCount": 28,
      "year": 734
    },
    {
      "id": "tang_057",
      "title": "送友人",
      "author": "李白",
      "dynasty": "唐",
      "dynastyCode": "tang",
      "content": "青山横北郭，白水绕东城。\n此地一为别，孤蓬万里征。\n浮云游子意，落日故人情。\n挥手自兹去，萧萧班马鸣。",
      "contentType": "poetry",
      "tags": [
        "五言律诗",
        "送别",
        "名篇",
        "初中必背"
      ],
      "source": "《李太白集》",
      "location": "安徽/宣城",
      "wordCount": 40,
      "year": 742
    },
    {
      "id": "tang_058",
      "title": "宣州谢朓楼饯别校书叔云",
      "author": "李白",
      "dynasty": "唐",
      "dynastyCode": "tang",
      "content": "弃我去者，昨日之日不可留；\n乱我心者，今日之日多烦忧。\n长风万里送秋雁，对此可以酣高楼。\n蓬莱文章建安骨，中间小谢又清发。\n俱怀逸兴壮思飞，欲上青天览明月。\n抽刀断水水更流，举杯消愁愁更愁。\n人生在世不称意，明朝散发弄扁舟。",
      "contentType": "poetry",
      "tags": [
        "七言古诗",
        "豪放",
        "名篇",
        "高中必背"
      ],
      "source": "《李太白集》",
      "location": "宣州/安徽",
      "wordCount": 112,
      "year": 753
    },
    {
      "id": "tang_059",
      "title": "春夜喜雨",
      "author": "杜甫",
      "dynasty": "唐",
      "dynastyCode": "tang",
      "content": "好雨知时节，当春乃发生。\n随风潜入夜，润物细无声。\n野径云俱黑，江船火独明。\n晓看红湿处，花重锦官城。",
      "contentType": "poetry",
      "tags": [
        "五言律诗",
        "写景",
        "春天",
        "小学必背"
      ],
      "source": "《杜工部集》",
      "location": "成都",
      "wordCount": 40,
      "year": 761
    },
    {
      "id": "tang_060",
      "title": "绝句",
      "author": "杜甫",
      "dynasty": "唐",
      "dynastyCode": "tang",
      "content": "两个黄鹂鸣翠柳，一行白鹭上青天。\n窗含西岭千秋雪，门泊东吴万里船。",
      "contentType": "poetry",
      "tags": [
        "七言绝句",
        "写景",
        "春天",
        "小学必背"
      ],
      "source": "《杜工部集》",
      "location": "成都/草堂",
      "wordCount": 28,
      "year": 764
    },
    {
      "id": "tang_061",
      "title": "江南逢李龟年",
      "author": "杜甫",
      "dynasty": "唐",
      "dynastyCode": "tang",
      "content": "岐王宅里寻常见，崔九堂前几度闻。\n正是江南好风景，落花时节又逢君。",
      "contentType": "poetry",
      "tags": [
        "七言绝句",
        "感怀",
        "初中必背"
      ],
      "source": "《杜工部集》",
      "location": "江南/长沙",
      "wordCount": 28,
      "year": 770
    },
    {
      "id": "tang_062",
      "title": "蜀相",
      "author": "杜甫",
      "dynasty": "唐",
      "dynastyCode": "tang",
      "content": "丞相祠堂何处寻？锦官城外柏森森。\n映阶碧草自春色，隔叶黄鹂空好音。\n三顾频烦天下计，两朝开济老臣心。\n出师未捷身先死，长使英雄泪满襟。",
      "contentType": "poetry",
      "tags": [
        "七言律诗",
        "怀古",
        "名篇",
        "高中必背"
      ],
      "source": "《杜工部集》",
      "location": "成都/武侯祠",
      "wordCount": 56,
      "year": 760
    },
    {
      "id": "tang_063",
      "title": "登岳阳楼",
      "author": "杜甫",
      "dynasty": "唐",
      "dynastyCode": "tang",
      "content": "昔闻洞庭水，今上岳阳楼。\n吴楚东南坼，乾坤日夜浮。\n亲朋无一字，老病有孤舟。\n戎马关山北，凭轩涕泗流。",
      "contentType": "poetry",
      "tags": [
        "五言律诗",
        "写景",
        "感怀",
        "高中必背"
      ],
      "source": "《杜工部集》",
      "location": "岳阳楼/湖南",
      "wordCount": 40,
      "year": 768
    },
    {
      "id": "tang_064",
      "title": "闻官军收河南河北",
      "author": "杜甫",
      "dynasty": "唐",
      "dynastyCode": "tang",
      "content": "剑外忽传收蓟北，初闻涕泪满衣裳。\n却看妻子愁何在，漫卷诗书喜欲狂。\n白日放歌须纵酒，青春作伴好还乡。\n即从巴峡穿巫峡，便下襄阳向洛阳。",
      "contentType": "poetry",
      "tags": [
        "七言律诗",
        "爱国",
        "名篇",
        "初中必背"
      ],
      "source": "《杜工部集》",
      "location": "梓州/四川三台",
      "wordCount": 56,
      "year": 763
    },
    {
      "id": "tang_065",
      "title": "月夜忆舍弟",
      "author": "杜甫",
      "dynasty": "唐",
      "dynastyCode": "tang",
      "content": "戍鼓断人行，边秋一雁声。\n露从今夜白，月是故乡明。\n有弟皆分散，无家问死生。\n寄书长不达，况乃未休兵。",
      "contentType": "poetry",
      "tags": [
        "五言律诗",
        "思乡",
        "战争",
        "初中必背"
      ],
      "source": "《杜工部集》",
      "location": "秦州/甘肃天水",
      "wordCount": 40,
      "year": 759
    },
    {
      "id": "tang_066",
      "title": "鹿柴",
      "author": "王维",
      "dynasty": "唐",
      "dynastyCode": "tang",
      "content": "空山不见人，但闻人语响。\n返景入深林，复照青苔上。",
      "contentType": "poetry",
      "tags": [
        "五言绝句",
        "山水",
        "名篇",
        "小学必背"
      ],
      "source": "《王右丞集》",
      "location": "辋川/蓝田",
      "wordCount": 20,
      "year": 740
    },
    {
      "id": "tang_067",
      "title": "鸟鸣涧",
      "author": "王维",
      "dynasty": "唐",
      "dynastyCode": "tang",
      "content": "人闲桂花落，夜静春山空。\n月出惊山鸟，时鸣春涧中。",
      "contentType": "poetry",
      "tags": [
        "五言绝句",
        "山水",
        "春天",
        "小学必背"
      ],
      "source": "《王右丞集》",
      "location": "辋川/蓝田",
      "wordCount": 20,
      "year": 740
    },
    {
      "id": "tang_068",
      "title": "九月九日忆山东兄弟",
      "author": "王维",
      "dynasty": "唐",
      "dynastyCode": "tang",
      "content": "独在异乡为异客，每逢佳节倍思亲。\n遥知兄弟登高处，遍插茱萸少一人。",
      "contentType": "poetry",
      "tags": [
        "七言绝句",
        "思乡",
        "名篇",
        "小学必背"
      ],
      "source": "《王右丞集》",
      "location": "长安",
      "wordCount": 28,
      "year": 718
    },
    {
      "id": "tang_069",
      "title": "相思",
      "author": "王维",
      "dynasty": "唐",
      "dynastyCode": "tang",
      "content": "红豆生南国，春来发几枝。\n愿君多采撷，此物最相思。",
      "contentType": "poetry",
      "tags": [
        "五言绝句",
        "爱情",
        "名篇",
        "小学必背"
      ],
      "source": "《王右丞集》",
      "location": "长安",
      "wordCount": 20,
      "year": 735
    },
    {
      "id": "tang_070",
      "title": "竹里馆",
      "author": "王维",
      "dynasty": "唐",
      "dynastyCode": "tang",
      "content": "独坐幽篁里，弹琴复长啸。\n深林人不知，明月来相照。",
      "contentType": "poetry",
      "tags": [
        "五言绝句",
        "山水",
        "闲适",
        "小学必背"
      ],
      "source": "《王右丞集》",
      "location": "辋川/蓝田",
      "wordCount": 20,
      "year": 740
    },
    {
      "id": "tang_071",
      "title": "忆江南",
      "author": "白居易",
      "dynasty": "唐",
      "dynastyCode": "tang",
      "content": "江南好，风景旧曾谙。\n日出江花红胜火，春来江水绿如蓝。\n能不忆江南？",
      "contentType": "poetry",
      "tags": [
        "词",
        "写景",
        "名篇",
        "小学必背"
      ],
      "source": "《白氏长庆集》",
      "location": "洛阳",
      "wordCount": 27,
      "year": 838
    },
    {
      "id": "tang_072",
      "title": "大林寺桃花",
      "author": "白居易",
      "dynasty": "唐",
      "dynastyCode": "tang",
      "content": "人间四月芳菲尽，山寺桃花始盛开。\n长恨春归无觅处，不知转入此中来。",
      "contentType": "poetry",
      "tags": [
        "七言绝句",
        "写景",
        "哲理",
        "小学必背"
      ],
      "source": "《白氏长庆集》",
      "location": "庐山/大林寺",
      "wordCount": 28,
      "year": 817
    },
    {
      "id": "tang_073",
      "title": "观刈麦",
      "author": "白居易",
      "dynasty": "唐",
      "dynastyCode": "tang",
      "content": "田家少闲月，五月人倍忙。\n夜来南风起，小麦覆陇黄。\n妇姑荷箪食，童稚携壶浆。\n相随饷田去，丁壮在南冈。\n足蒸暑土气，背灼炎天光。\n力尽不知热，但惜夏日长。\n复有贫妇人，抱子在其旁。\n右手秉遗穗，左臂悬敝筐。\n听其相顾言，闻者为悲伤。\n家田输税尽，拾此充饥肠。\n今我何功德，曾不事农桑。\n吏禄三百石，岁晏有余粮。\n念此私自愧，尽日不能忘。",
      "contentType": "poetry",
      "tags": [
        "五言古诗",
        "讽喻",
        "民生",
        "初中必背"
      ],
      "source": "《白氏长庆集》",
      "location": "周至/陕西",
      "wordCount": 190,
      "year": 806
    },
    {
      "id": "tang_074",
      "title": "长恨歌（节选）",
      "author": "白居易",
      "dynasty": "唐",
      "dynastyCode": "tang",
      "content": "汉皇重色思倾国，御宇多年求不得。\n杨家有女初长成，养在深闺人未识。\n天生丽质难自弃，一朝选在君王侧。\n回眸一笑百媚生，六宫粉黛无颜色。\n\n春寒赐浴华清池，温泉水滑洗凝脂。\n侍儿扶起娇无力，始是新承恩泽时。\n\n七月七日长生殿，夜半无人私语时。\n在天愿作比翼鸟，在地愿为连理枝。\n天长地久有时尽，此恨绵绵无绝期。",
      "contentType": "poetry",
      "tags": [
        "七言古诗",
        "叙事",
        "爱情",
        "高中必背"
      ],
      "source": "《白氏长庆集》",
      "location": "长安/华清宫",
      "wordCount": 170,
      "year": 806
    },
    {
      "id": "tang_075",
      "title": "暮江吟",
      "author": "白居易",
      "dynasty": "唐",
      "dynastyCode": "tang",
      "content": "一道残阳铺水中，半江瑟瑟半江红。\n可怜九月初三夜，露似真珠月似弓。",
      "contentType": "poetry",
      "tags": [
        "七言绝句",
        "写景",
        "名篇",
        "小学必背"
      ],
      "source": "《白氏长庆集》",
      "location": "江州/九江",
      "wordCount": 28,
      "year": 822
    },
    {
      "id": "tang_076",
      "title": "嫦娥",
      "author": "李商隐",
      "dynasty": "唐",
      "dynastyCode": "tang",
      "content": "云母屏风烛影深，长河渐落晓星沉。\n嫦娥应悔偷灵药，碧海青天夜夜心。",
      "contentType": "poetry",
      "tags": [
        "七言绝句",
        "咏物",
        "神话",
        "小学必背"
      ],
      "source": "《李义山诗集》",
      "location": "长安",
      "wordCount": 28,
      "year": 850
    },
    {
      "id": "tang_077",
      "title": "贾生",
      "author": "李商隐",
      "dynasty": "唐",
      "dynastyCode": "tang",
      "content": "宣室求贤访逐臣，贾生才调更无伦。\n可怜夜半虚前席，不问苍生问鬼神。",
      "contentType": "poetry",
      "tags": [
        "七言绝句",
        "咏史",
        "讽刺",
        "初中必背"
      ],
      "source": "《李义山诗集》",
      "location": "长安",
      "wordCount": 28,
      "year": 848
    },
    {
      "id": "tang_078",
      "title": "登乐游原",
      "author": "李商隐",
      "dynasty": "唐",
      "dynastyCode": "tang",
      "content": "向晚意不适，驱车登古原。\n夕阳无限好，只是近黄昏。",
      "contentType": "poetry",
      "tags": [
        "五言绝句",
        "感怀",
        "名篇",
        "小学必背"
      ],
      "source": "《李义山诗集》",
      "location": "乐游原/西安",
      "wordCount": 20,
      "year": 855
    },
    {
      "id": "tang_079",
      "title": "山行",
      "author": "杜牧",
      "dynasty": "唐",
      "dynastyCode": "tang",
      "content": "远上寒山石径斜，白云深处有人家。\n停车坐爱枫林晚，霜叶红于二月花。",
      "contentType": "poetry",
      "tags": [
        "七言绝句",
        "写景",
        "秋天",
        "小学必背"
      ],
      "source": "《樊川文集》",
      "location": "长安/终南山",
      "wordCount": 28,
      "year": 840
    },
    {
      "id": "tang_080",
      "title": "清明",
      "author": "杜牧",
      "dynasty": "唐",
      "dynastyCode": "tang",
      "content": "清明时节雨纷纷，路上行人欲断魂。\n借问酒家何处有，牧童遥指杏花村。",
      "contentType": "poetry",
      "tags": [
        "七言绝句",
        "节日",
        "名篇",
        "小学必背"
      ],
      "source": "《樊川文集》",
      "location": "池州/安徽",
      "wordCount": 28,
      "year": 845
    },
    {
      "id": "tang_081",
      "title": "秋夕",
      "author": "杜牧",
      "dynasty": "唐",
      "dynastyCode": "tang",
      "content": "银烛秋光冷画屏，轻罗小扇扑流萤。\n天阶夜色凉如水，卧看牵牛织女星。",
      "contentType": "poetry",
      "tags": [
        "七言绝句",
        "宫怨",
        "秋天",
        "小学必背"
      ],
      "source": "《樊川文集》",
      "location": "长安",
      "wordCount": 28,
      "year": 840
    },
    {
      "id": "tang_082",
      "title": "芙蓉楼送辛渐",
      "author": "王昌龄",
      "dynasty": "唐",
      "dynastyCode": "tang",
      "content": "寒雨连江夜入吴，平明送客楚山孤。\n洛阳亲友如相问，一片冰心在玉壶。",
      "contentType": "poetry",
      "tags": [
        "七言绝句",
        "送别",
        "名篇",
        "小学必背"
      ],
      "source": "《全唐诗》",
      "location": "芙蓉楼/镇江",
      "wordCount": 28,
      "year": 740
    },
    {
      "id": "tang_083",
      "title": "从军行七首·其四",
      "author": "王昌龄",
      "dynasty": "唐",
      "dynastyCode": "tang",
      "content": "青海长云暗雪山，孤城遥望玉门关。\n黄沙百战穿金甲，不破楼兰终不还。",
      "contentType": "poetry",
      "tags": [
        "七言绝句",
        "边塞",
        "壮志",
        "小学必背"
      ],
      "source": "《全唐诗》",
      "location": "边塞/甘肃",
      "wordCount": 28,
      "year": 740
    },
    {
      "id": "tang_084",
      "title": "悯农（其二）",
      "author": "李绅",
      "dynasty": "唐",
      "dynastyCode": "tang",
      "content": "锄禾日当午，汗滴禾下土。\n谁知盘中餐，粒粒皆辛苦。",
      "contentType": "poetry",
      "tags": [
        "五言绝句",
        "讽喻",
        "民生",
        "小学必背"
      ],
      "source": "《全唐诗》",
      "location": "长安",
      "wordCount": 20,
      "year": 800
    },
    {
      "id": "tang_085",
      "title": "塞下曲",
      "author": "卢纶",
      "dynasty": "唐",
      "dynastyCode": "tang",
      "content": "月黑雁飞高，单于夜遁逃。\n欲将轻骑逐，大雪满弓刀。",
      "contentType": "poetry",
      "tags": [
        "五言绝句",
        "边塞",
        "小学必背"
      ],
      "source": "《全唐诗》",
      "location": "边塞",
      "wordCount": 20,
      "year": 770
    },
    {
      "id": "tang_086",
      "title": "寻隐者不遇",
      "author": "贾岛",
      "dynasty": "唐",
      "dynastyCode": "tang",
      "content": "松下问童子，言师采药去。\n只在此山中，云深不知处。",
      "contentType": "poetry",
      "tags": [
        "五言绝句",
        "问答",
        "隐逸",
        "小学必背"
      ],
      "source": "《长江集》",
      "location": "长安/终南山",
      "wordCount": 20,
      "year": 810
    },
    {
      "id": "tang_087",
      "title": "望月怀远",
      "author": "张九龄",
      "dynasty": "唐",
      "dynastyCode": "tang",
      "content": "海上生明月，天涯共此时。\n情人怨遥夜，竟夕起相思。\n灭烛怜光满，披衣觉露滋。\n不堪盈手赠，还寝梦佳期。",
      "contentType": "poetry",
      "tags": [
        "五言律诗",
        "思乡",
        "名篇",
        "高中必背"
      ],
      "source": "《曲江集》",
      "location": "荆州",
      "wordCount": 40,
      "year": 735
    },
    {
      "id": "tang_088",
      "title": "秋词",
      "author": "刘禹锡",
      "dynasty": "唐",
      "dynastyCode": "tang",
      "content": "自古逢秋悲寂寥，我言秋日胜春朝。\n晴空一鹤排云上，便引诗情到碧霄。",
      "contentType": "poetry",
      "tags": [
        "七言绝句",
        "哲理",
        "豪迈",
        "初中必背"
      ],
      "source": "《刘梦得文集》",
      "location": "朗州/湖南常德",
      "wordCount": 28,
      "year": 805
    },
    {
      "id": "tang_089",
      "title": "乌衣巷",
      "author": "刘禹锡",
      "dynasty": "唐",
      "dynastyCode": "tang",
      "content": "朱雀桥边野草花，乌衣巷口夕阳斜。\n旧时王谢堂前燕，飞入寻常百姓家。",
      "contentType": "poetry",
      "tags": [
        "七言绝句",
        "怀古",
        "名篇",
        "小学必背"
      ],
      "source": "《刘梦得文集》",
      "location": "金陵/南京",
      "wordCount": 28,
      "year": 826
    },
    {
      "id": "tang_090",
      "title": "浪淘沙",
      "author": "刘禹锡",
      "dynasty": "唐",
      "dynastyCode": "tang",
      "content": "九曲黄河万里沙，浪淘风簸自天涯。\n如今直上银河去，同到牵牛织女家。",
      "contentType": "poetry",
      "tags": [
        "七言绝句",
        "写景",
        "神话",
        "小学必背"
      ],
      "source": "《刘梦得文集》",
      "location": "夔州/重庆",
      "wordCount": 28,
      "year": 820
    },
    {
      "id": "tang_091",
      "title": "过故人庄",
      "author": "孟浩然",
      "dynasty": "唐",
      "dynastyCode": "tang",
      "content": "故人具鸡黍，邀我至田家。\n绿树村边合，青山郭外斜。\n开轩面场圃，把酒话桑麻。\n待到重阳日，还来就菊花。",
      "contentType": "poetry",
      "tags": [
        "五言律诗",
        "田园",
        "友情",
        "小学必背"
      ],
      "source": "《孟浩然集》",
      "location": "襄阳/湖北",
      "wordCount": 40,
      "year": 730
    },
    {
      "id": "tang_092",
      "title": "宿建德江",
      "author": "孟浩然",
      "dynasty": "唐",
      "dynastyCode": "tang",
      "content": "移舟泊烟渚，日暮客愁新。\n野旷天低树，江清月近人。",
      "contentType": "poetry",
      "tags": [
        "五言绝句",
        "羁旅",
        "写景",
        "小学必背"
      ],
      "source": "《孟浩然集》",
      "location": "建德江/浙江",
      "wordCount": 20,
      "year": 728
    },
    {
      "id": "tang_093",
      "title": "早春呈水部张十八员外",
      "author": "韩愈",
      "dynasty": "唐",
      "dynastyCode": "tang",
      "content": "天街小雨润如酥，草色遥看近却无。\n最是一年春好处，绝胜烟柳满皇都。",
      "contentType": "poetry",
      "tags": [
        "七言绝句",
        "写景",
        "春天",
        "初中必背"
      ],
      "source": "《昌黎先生集》",
      "location": "长安",
      "wordCount": 28,
      "year": 823
    },
    {
      "id": "tang_094",
      "title": "逢入京使",
      "author": "岑参",
      "dynasty": "唐",
      "dynastyCode": "tang",
      "content": "故园东望路漫漫，双袖龙钟泪不干。\n马上相逢无纸笔，凭君传语报平安。",
      "contentType": "poetry",
      "tags": [
        "七言绝句",
        "边塞",
        "思乡",
        "初中必背"
      ],
      "source": "《岑嘉州集》",
      "location": "西域/安西",
      "wordCount": 28,
      "year": 749
    },
    {
      "id": "tang_095",
      "title": "商山早行",
      "author": "温庭筠",
      "dynasty": "唐",
      "dynastyCode": "tang",
      "content": "晨起动征铎，客行悲故乡。\n鸡声茅店月，人迹板桥霜。\n槲叶落山路，枳花明驿墙。\n因思杜陵梦，凫雁满回塘。",
      "contentType": "poetry",
      "tags": [
        "五言律诗",
        "羁旅",
        "名篇",
        "初中必背"
      ],
      "source": "《温庭筠全集》",
      "location": "商山/陕西",
      "wordCount": 40,
      "year": 840
    },
    {
      "id": "tang_096",
      "title": "夜上受降城闻笛",
      "author": "李益",
      "dynasty": "唐",
      "dynastyCode": "tang",
      "content": "回乐峰前沙似雪，受降城外月如霜。\n不知何处吹芦管，一夜征人尽望乡。",
      "contentType": "poetry",
      "tags": [
        "七言绝句",
        "边塞",
        "思乡",
        "初中必背"
      ],
      "source": "《全唐诗》",
      "location": "受降城/宁夏灵武",
      "wordCount": 28,
      "year": 780
    },
    {
      "id": "tang_097",
      "title": "十五夜望月",
      "author": "王建",
      "dynasty": "唐",
      "dynastyCode": "tang",
      "content": "中庭地白树栖鸦，冷露无声湿桂花。\n今夜月明人尽望，不知秋思落谁家。",
      "contentType": "poetry",
      "tags": [
        "七言绝句",
        "中秋",
        "思乡",
        "小学必背"
      ],
      "source": "《王建诗集》",
      "location": "长安",
      "wordCount": 28,
      "year": 810
    },
    {
      "id": "tang_098",
      "title": "渔歌子",
      "author": "张志和",
      "dynasty": "唐",
      "dynastyCode": "tang",
      "content": "西塞山前白鹭飞，桃花流水鳜鱼肥。\n青箬笠，绿蓑衣，斜风细雨不须归。",
      "contentType": "poetry",
      "tags": [
        "词",
        "山水",
        "隐逸",
        "小学必背"
      ],
      "source": "《全唐诗》",
      "location": "西塞山/浙江湖州",
      "wordCount": 27,
      "year": 770
    },
    {
      "id": "tang_099",
      "title": "蝉",
      "author": "虞世南",
      "dynasty": "唐",
      "dynastyCode": "tang",
      "content": "垂緌饮清露，流响出疏桐。\n居高声自远，非是藉秋风。",
      "contentType": "poetry",
      "tags": [
        "五言绝句",
        "咏物",
        "哲理",
        "小学必背"
      ],
      "source": "《全唐诗》",
      "location": "长安",
      "wordCount": 20,
      "year": 630
    },
    {
      "id": "tang_100",
      "title": "逢雪宿芙蓉山主人",
      "author": "刘长卿",
      "dynasty": "唐",
      "dynastyCode": "tang",
      "content": "日暮苍山远，天寒白屋贫。\n柴门闻犬吠，风雪夜归人。",
      "contentType": "poetry",
      "tags": [
        "五言绝句",
        "写景",
        "羁旅",
        "小学必背"
      ],
      "source": "《刘随州诗集》",
      "location": "芙蓉山/湖南",
      "wordCount": 20,
      "year": 770
    },
    {
      "id": "tang_101",
      "title": "题破山寺后禅院",
      "author": "常建",
      "dynasty": "唐",
      "dynastyCode": "tang",
      "content": "清晨入古寺，初日照高林。\n曲径通幽处，禅房花木深。\n山光悦鸟性，潭影空人心。\n万籁此都寂，但余钟磬音。",
      "contentType": "poetry",
      "tags": [
        "五言律诗",
        "山水",
        "禅意",
        "初中必背"
      ],
      "source": "《常建集》",
      "location": "破山寺/江苏常熟",
      "wordCount": 40,
      "year": 745
    },
    {
      "id": "tang_102",
      "title": "蜂",
      "author": "罗隐",
      "dynasty": "唐",
      "dynastyCode": "tang",
      "content": "不论平地与山尖，无限风光尽被占。\n采得百花成蜜后，为谁辛苦为谁甜？",
      "contentType": "poetry",
      "tags": [
        "七言绝句",
        "咏物",
        "哲理",
        "小学必背"
      ],
      "source": "《罗隐集》",
      "location": "长安",
      "wordCount": 28,
      "year": 870
    },
    {
      "id": "tang_103",
      "title": "金铜仙人辞汉歌（节选）",
      "author": "李贺",
      "dynasty": "唐",
      "dynastyCode": "tang",
      "content": "茂陵刘郎秋风客，夜闻马嘶晓无迹。\n画栏桂树悬秋香，三十六宫土花碧。\n魏官牵车指千里，东关酸风射眸子。\n空将汉月出宫门，忆君清泪如铅水。\n衰兰送客咸阳道，天若有情天亦老。\n携盘独出月荒凉，渭城已远波声小。",
      "contentType": "poetry",
      "tags": [
        "七言古诗",
        "咏史",
        "名句",
        "高中必背"
      ],
      "source": "《李长吉歌诗》",
      "location": "长安",
      "wordCount": 132,
      "year": 810
    },
    {
      "id": "tang_104",
      "title": "峨眉山月歌",
      "author": "李白",
      "dynasty": "唐",
      "dynastyCode": "tang",
      "content": "峨眉山月半轮秋，影入平羌江水流。\n夜发清溪向三峡，思君不见下渝州。",
      "contentType": "poetry",
      "tags": [
        "七言绝句",
        "山水",
        "思乡",
        "初中必背"
      ],
      "source": "《李太白集》",
      "location": "峨眉山/四川",
      "wordCount": 28,
      "year": 724
    },
    {
      "id": "tang_105",
      "title": "金陵酒肆留别",
      "author": "李白",
      "dynasty": "唐",
      "dynastyCode": "tang",
      "content": "风吹柳花满店香，吴姬压酒劝客尝。\n金陵子弟来相送，欲行不行各尽觞。\n请君试问东流水，别意与之谁短长。",
      "contentType": "poetry",
      "tags": [
        "七言古诗",
        "送别",
        "名篇",
        "高中必背"
      ],
      "source": "《李太白集》",
      "location": "金陵/南京",
      "wordCount": 48,
      "year": 739
    },
    {
      "id": "tang_106",
      "title": "旅夜书怀",
      "author": "杜甫",
      "dynasty": "唐",
      "dynastyCode": "tang",
      "content": "细草微风岸，危樯独夜舟。\n星垂平野阔，月涌大江流。\n名岂文章著，官应老病休。\n飘飘何所似，天地一沙鸥。",
      "contentType": "poetry",
      "tags": [
        "五言律诗",
        "感怀",
        "名篇",
        "高中必背"
      ],
      "source": "《杜工部集》",
      "location": "渝州/重庆",
      "wordCount": 40,
      "year": 765
    },
    {
      "id": "tang_107",
      "title": "赠花卿",
      "author": "杜甫",
      "dynasty": "唐",
      "dynastyCode": "tang",
      "content": "锦城丝管日纷纷，半入江风半入云。\n此曲只应天上有，人间能得几回闻。",
      "contentType": "poetry",
      "tags": [
        "七言绝句",
        "音乐",
        "名篇",
        "小学必背"
      ],
      "source": "《杜工部集》",
      "location": "成都",
      "wordCount": 28,
      "year": 761
    },
    {
      "id": "tang_108",
      "title": "画",
      "author": "王维",
      "dynasty": "唐",
      "dynastyCode": "tang",
      "content": "远看山有色，近听水无声。\n春去花还在，人来鸟不惊。",
      "contentType": "poetry",
      "tags": [
        "五言绝句",
        "题画",
        "启蒙",
        "小学必背"
      ],
      "source": "《全唐诗》",
      "location": "长安",
      "wordCount": 20,
      "year": 740
    },
    {
      "id": "tang_109",
      "title": "凉州词",
      "author": "王之涣",
      "dynasty": "唐",
      "dynastyCode": "tang",
      "content": "黄河远上白云间，一片孤城万仞山。\n羌笛何须怨杨柳，春风不度玉门关。",
      "contentType": "poetry",
      "tags": [
        "七言绝句",
        "边塞",
        "名篇",
        "小学必背"
      ],
      "source": "《全唐诗》",
      "location": "凉州/甘肃",
      "wordCount": 28,
      "year": 720
    },
    {
      "id": "tang_110",
      "title": "滕王阁诗",
      "author": "王勃",
      "dynasty": "唐",
      "dynastyCode": "tang",
      "content": "滕王高阁临江渚，佩玉鸣鸾罢歌舞。\n画栋朝飞南浦云，珠帘暮卷西山雨。\n闲云潭影日悠悠，物换星移几度秋。\n阁中帝子今何在？槛外长江空自流。",
      "contentType": "poetry",
      "tags": [
        "七言古诗",
        "怀古",
        "名篇",
        "高中必背"
      ],
      "source": "《王子安集》",
      "location": "滕王阁/南昌",
      "wordCount": 56,
      "year": 676
    },
    {
      "id": "tang_111",
      "title": "问刘十九",
      "author": "白居易",
      "dynasty": "唐",
      "dynastyCode": "tang",
      "content": "绿蚁新醅酒，红泥小火炉。\n晚来天欲雪，能饮一杯无？",
      "contentType": "poetry",
      "tags": [
        "五言绝句",
        "友情",
        "闲适",
        "小学必背"
      ],
      "source": "《白氏长庆集》",
      "location": "江州/九江",
      "wordCount": 20,
      "year": 817
    },
    {
      "id": "tang_112",
      "title": "过华清宫",
      "author": "杜牧",
      "dynasty": "唐",
      "dynastyCode": "tang",
      "content": "长安回望绣成堆，山顶千门次第开。\n一骑红尘妃子笑，无人知是荔枝来。",
      "contentType": "poetry",
      "tags": [
        "七言绝句",
        "咏史",
        "讽刺",
        "初中必背"
      ],
      "source": "《樊川文集》",
      "location": "华清宫/临潼",
      "wordCount": 28,
      "year": 846
    },
    {
      "id": "tang_113",
      "title": "左迁至蓝关示侄孙湘",
      "author": "韩愈",
      "dynasty": "唐",
      "dynastyCode": "tang",
      "content": "一封朝奏九重天，夕贬潮州路八千。\n欲为圣明除弊事，肯将衰朽惜残年！\n云横秦岭家何在？雪拥蓝关马不前。\n知汝远来应有意，好收吾骨瘴江边。",
      "contentType": "poetry",
      "tags": [
        "七言律诗",
        "感怀",
        "贬谪",
        "初中必背"
      ],
      "source": "《昌黎先生集》",
      "location": "蓝关/陕西",
      "wordCount": 56,
      "year": 819
    },
    {
      "id": "tang_114",
      "title": "燕歌行（节选）",
      "author": "高适",
      "dynasty": "唐",
      "dynastyCode": "tang",
      "content": "汉家烟尘在东北，汉将辞家破残贼。\n男儿本自重横行，天子非常赐颜色。\n\n战士军前半死生，美人帐下犹歌舞。\n大漠穷秋塞草腓，孤城落日斗兵稀。\n\n君不见沙场征战苦，至今犹忆李将军。",
      "contentType": "poetry",
      "tags": [
        "七言古诗",
        "边塞",
        "名篇",
        "高中必背"
      ],
      "source": "《高常侍集》",
      "location": "蓟北/河北",
      "wordCount": 130,
      "year": 734
    },
    {
      "id": "tang_115",
      "title": "寒食",
      "author": "韩翃",
      "dynasty": "唐",
      "dynastyCode": "tang",
      "content": "春城无处不飞花，寒食东风御柳斜。\n日暮汉宫传蜡烛，轻烟散入五侯家。",
      "contentType": "poetry",
      "tags": [
        "七言绝句",
        "节日",
        "讽刺",
        "小学必背"
      ],
      "source": "《全唐诗》",
      "location": "长安",
      "wordCount": 28,
      "year": 760
    },
    {
      "id": "tang_116",
      "title": "行路难·其二",
      "author": "李白",
      "dynasty": "唐",
      "dynastyCode": "tang",
      "content": "大道如青天，我独不得出。\n羞逐长安社中儿，赤鸡白雉赌梨栗。\n弹剑作歌奏苦声，曳裾王门不称情。\n淮阴市井笑韩信，汉朝公卿忌贾生。\n君不见昔时燕家重郭隗，拥篲折节无嫌猜。\n剧辛乐毅感恩分，输肝剖胆效英才。\n昭王白骨萦蔓草，谁人更扫黄金台？\n行路难，归去来！",
      "contentType": "poetry",
      "tags": [
        "七言古诗",
        "感怀",
        "豪放",
        "高中必背"
      ],
      "source": "《李太白集》",
      "location": "长安",
      "wordCount": 120,
      "year": 744
    },
    {
      "id": "tang_117",
      "title": "秋思",
      "author": "张籍",
      "dynasty": "唐",
      "dynastyCode": "tang",
      "content": "洛阳城里见秋风，欲作家书意万重。\n复恐匆匆说不尽，行人临发又开封。",
      "contentType": "poetry",
      "tags": [
        "七言绝句",
        "思乡",
        "名篇",
        "小学必背"
      ],
      "source": "《全唐诗》",
      "location": "洛阳",
      "wordCount": 28,
      "year": 810
    },
    {
      "id": "tang_118",
      "title": "滁州西涧",
      "author": "韦应物",
      "dynasty": "唐",
      "dynastyCode": "tang",
      "content": "独怜幽草涧边生，上有黄鹂深树鸣。\n春潮带雨晚来急，野渡无人舟自横。",
      "contentType": "poetry",
      "tags": [
        "七言绝句",
        "山水",
        "恬淡",
        "初中必背"
      ],
      "source": "《韦苏州集》",
      "location": "滁州/安徽",
      "wordCount": 28,
      "year": 783
    },
    {
      "id": "tang_119",
      "title": "凉州词",
      "author": "王翰",
      "dynasty": "唐",
      "dynastyCode": "tang",
      "content": "葡萄美酒夜光杯，欲饮琵琶马上催。\n醉卧沙场君莫笑，古来征战几人回？",
      "contentType": "poetry",
      "tags": [
        "七言绝句",
        "边塞",
        "豪迈",
        "小学必背"
      ],
      "source": "《全唐诗》",
      "location": "凉州/甘肃",
      "wordCount": 28,
      "year": 710
    },
    {
      "id": "tang_120",
      "title": "望天门山",
      "author": "李白",
      "dynasty": "唐",
      "dynastyCode": "tang",
      "content": "天门中断楚江开，碧水东流至此回。\n两岸青山相对出，孤帆一片日边来。",
      "contentType": "poetry",
      "tags": [
        "七言绝句",
        "山水",
        "小学必背"
      ],
      "source": "《李太白集》",
      "location": "天门山/安徽",
      "wordCount": 28,
      "year": 725
    }
  ]
}
